LICENSE
MANIFEST.in
setup.cfg
setup.py
scanpkg/__init__.py
scanpkg/__version__.py
scanpkg/scanpkg.py
scanpkg.egg-info/PKG-INFO
scanpkg.egg-info/SOURCES.txt
scanpkg.egg-info/dependency_links.txt
scanpkg.egg-info/entry_points.txt
scanpkg.egg-info/requires.txt
scanpkg.egg-info/top_level.txt
scanpkg/bin/ar.exe
scanpkg/bin/libcharset1.dll
scanpkg/bin/libiconv2.dll
scanpkg/bin/libintl-2.dll
scanpkg/bin/sha1sum.exe
scanpkg/bin/sha256sum.exe
scanpkg/bin/tar.exe