Metadata-Version: 1.1
Name: scanpkg
Version: 0.0.3
Summary: Windows alternative for dpkg-scanpackages (mainly created for cydia repos, but should work with other Debian repos)
Home-page: https://github.com/mstg/scanpkg
Author: mstg
Author-email: mustiigezen@gmail.com
License: The MIT License (MIT)
